a_rtl/apb_slave.v
`timescale 1ns/1ps

module apb_slave(
    input pclk,
    input presetn,
    input [31:0] paddr,
    input psel,
    input penable,
    input [7:0] pwdata,
    input pwrite,
    output reg [7:0] prdata,
    output reg pready
);

    reg [7:0] mem [0:15];

    always @(posedge pclk or negedge presetn) 
    begin
        if(!presetn) 
        begin
            pready <= 0;
            prdata <= 8'h00;
        end 
        
        else 
        begin
            pready <= 0;
            if(psel && penable) 
            begin
                pready <= 1;
                if(pwrite)
                    mem[paddr] <= pwdata;
                else
                    prdata <= mem[paddr];
            end
        end
    end

endmodule

d_tb/apb_tb.v
`timescale 1ns/1ps

module apb_slave_tb;

    reg pclk;
    reg presetn;
    reg [31:0] paddr;
    reg [7:0] pwdata;
    reg psel;
    reg penable;
    reg pwrite;
    wire [7:0] prdata;
    wire pready;

    apb_slave dut (
        .pclk(pclk),
        .presetn(presetn),
        .paddr(paddr),
        .pwdata(pwdata),
        .psel(psel),
        .penable(penable),
        .pwrite(pwrite),
        .prdata(prdata),
        .pready(pready)
    );

    initial pclk = 0;
    always #5 pclk = ~pclk;

    initial begin
        presetn = 0;
        psel = 0;
        penable = 0;
        pwrite = 0;
        paddr = 0;
        pwdata = 0;
        #20 presetn = 1;
    end

    task apb_write;
        input [31:0] addr;
        input [7:0] data;
    begin
        paddr = addr;
        pwdata = data;
        pwrite = 1;
        psel = 1;
        penable = 0;
        @(posedge pclk);
        penable = 1;
        @(posedge pclk);
        penable = 0;
        psel = 0;
        pwrite = 0;
        @(posedge pclk);
    end
    endtask
    
    reg [7:0] rdata;
    task apb_read;
        input [31:0] addr;
    begin
        paddr = addr;
        pwrite = 0;
        psel = 1;
        penable = 0;
        @(posedge pclk);
        penable = 1;
        @(posedge pclk);
        rdata = prdata;
        penable = 0;
        psel = 0;
        @(posedge pclk);
    end
    endtask

    initial begin
        $dumpfile("apb_slave.vcd");
        $dumpvars(0, apb_slave_tb);

        wait(presetn == 1);

        apb_write(32'h02, 8'hAA);
        
        @(posedge pclk);
        
         apb_write(32'h05, 8'h55);
        @(posedge pclk);
        
        
        apb_read(32'h05);
        $display("Read value = 0x%h (should be 0x55)", rdata);

        
        apb_read(32'h02);
        $display("Read value = 0x%h (should be 0xaa)", rdata);

        #20 $finish;
    end

endmodule

apb_slave.vcd
$date
	Thu Nov 20 12:06:12 2025
$end
$version
	Icarus Verilog
$end
$timescale
	1ps
$end
$scope module apb_slave_tb $end
$var wire 1 ! pready $end
$var wire 8 " prdata [7:0] $end
$var reg 32 # paddr [31:0] $end
$var reg 1 $ pclk $end
$var reg 1 % penable $end
$var reg 1 & presetn $end
$var reg 1 ' psel $end
$var reg 8 ( pwdata [7:0] $end
$var reg 1 ) pwrite $end
$var reg 8 * rdata [7:0] $end
$scope module dut $end
$var wire 32 + paddr [31:0] $end
$var wire 1 $ pclk $end
$var wire 1 % penable $end
$var wire 1 & presetn $end
$var wire 1 ' psel $end
$var wire 8 , pwdata [7:0] $end
$var wire 1 ) pwrite $end
$var reg 8 - prdata [7:0] $end
$var reg 1 ! pready $end
$upscope $end
$scope task apb_read $end
$var reg 32 . addr [31:0] $end
$upscope $end
$scope task apb_write $end
$var reg 32 / addr [31:0] $end
$var reg 8 0 data [7:0] $end
$upscope $end
$upscope $end
$enddefinitions $end
$comment Show the parameter values. $end
$dumpall
$end
#0
$dumpvars
bx 0
bx /
bx .
b0 -
b0 ,
b0 +
bx *
0)
b0 (
0'
0&
0%
0$
b0 #
b0 "
0!
$end
#5000
1$
#10000
0$
#15000
1$
#20000
1'
1)
b10101010 (
b10101010 ,
b10 #
b10 +
b10101010 0
b10 /
0$
1&
#25000
1!
1%
1$
#30000
0$
#35000
0!
0)
0'
0%
1$
#40000
0$
#45000
1$
#50000
0$
#55000
1'
1)
b1010101 (
b1010101 ,
b101 #
b101 +
b1010101 0
b101 /
1$
#60000
0$
#65000
1!
1%
1$
#70000
0$
#75000
0!
0)
0'
0%
1$
#80000
0$
#85000
1$
#90000
0$
#95000
1'
b101 .
1$
#100000
0$
#105000
b1010101 "
b1010101 -
1!
1%
1$
#110000
0$
#115000
0!
0'
0%
b1010101 *
1$
#120000
0$
#125000
1'
b10 #
b10 +
b10 .
1$
#130000
0$
#135000
b10101010 "
b10101010 -
1!
1%
1$
#140000
0$
#145000
0!
0'
0%
b10101010 *
1$
